splatprint/__init__.py
splatprint/macropreview.py
splatprint/printpost.py
splatprint/repairpost.py
splatprint/splatprint.py
splatprint/test.py
splatprint-1.0.3.dist-info/LICENSE.md
splatprint-1.0.3.dist-info/METADATA
splatprint-1.0.3.dist-info/WHEEL
splatprint-1.0.3.dist-info/entry_points.txt
splatprint-1.0.3.dist-info/top_level.txt
splatprint-1.0.3.dist-info/RECORD
